kozmoai_regulators/__init__.py
kozmoai_regulators/cftc/__init__.py
kozmoai_regulators/cftc/cftc_router.py
kozmoai_regulators/regulators_router.py
kozmoai_regulators/sec/__init__.py
kozmoai_regulators/sec/sec_router.py
kozmoai_regulators-1.4.1.dev202506081902.dist-info/METADATA
kozmoai_regulators-1.4.1.dev202506081902.dist-info/WHEEL
kozmoai_regulators-1.4.1.dev202506081902.dist-info/entry_points.txt
kozmoai_regulators-1.4.1.dev202506081902.dist-info/RECORD
